lazi/auto.py
lazi/conf/auto.py
lazi/conf/base.py
lazi/conf/conf.py
lazi/conf/envs.py
lazi/conf/lazy.py
lazi/core/__init__.py
lazi/core/finder.py
lazi/core/loader.py
lazi/core/module.py
lazi/core/spec.py
lazi/core/stat.py
lazi/util/__init__.py
lazi/util/debug.py
lazi/util/functional.py
lazi/util/util.py
lazi-1.9.161.dist-info/METADATA
lazi-1.9.161.dist-info/WHEEL
lazi-1.9.161.dist-info/RECORD
