Metadata-Version: 2.1
Name: lazi
Version: 1.9.161
Summary: A lightweight and extensible way to implement lazy imports globally.
Home-page: https://github.com/sitbon/lazi
License: AGPLv3
Author: Phillip Sitbon
Author-email: phillip.sitbon@gmail.com
Requires-Python: >=3.10,<4.0
Classifier: Environment :: Web Environment
Classifier: Intended Audience :: Developers
Classifier: License :: OSI Approved :: GNU Affero General Public License v3 or later (AGPLv3+)
Classifier: License :: Other/Proprietary License
Classifier: Natural Language :: English
Classifier: Operating System :: OS Independent
Classifier: Programming Language :: Python
Classifier: Programming Language :: Python :: 3
Classifier: Programming Language :: Python :: 3.10
Classifier: Programming Language :: Python :: 3.11
Classifier: Programming Language :: Python :: 3 :: Only
Classifier: Topic :: Software Development :: Libraries
Project-URL: Repository, https://github.com/sitbon/lazi
